userElainaTestSetup1/__init__.py
userElainaTestSetup1/aa.py
userElainaTestSetup1-1.8.2.1.dist-info/LICENSE.txt
userElainaTestSetup1-1.8.2.1.dist-info/METADATA
userElainaTestSetup1-1.8.2.1.dist-info/WHEEL
userElainaTestSetup1-1.8.2.1.dist-info/entry_points.txt
userElainaTestSetup1-1.8.2.1.dist-info/top_level.txt
userElainaTestSetup1-1.8.2.1.dist-info/RECORD
