Metadata-Version: 2.1
Name: userElainaTestSetup1
Version: 1.8.2.1
Summary: Elaina's sample Python project
Author-email: userElaina <userelaina@pm.me>
Maintainer-email: userElaina <userelaina@pm.me>
License: Copyright (c) 2016 The Python Packaging Authority (PyPA)
Project-URL: Homepage, https://github.com/pypa/sampleproject
Project-URL: Bug Reports, https://github.com/pypa/sampleproject/issues
Project-URL: Funding, https://donate.pypi.org
Project-URL: Say Thanks!, http://saythanks.io/to/example
Project-URL: Source, https://github.com/pypa/sampleproject/
Keywords: sample,setuptools,development
Classifier: Programming Language :: Python :: 3
Requires-Python: >=3
License-File: LICENSE.txt
Requires-Dist: peppercorn
Requires-Dist: six
Provides-Extra: dev
Requires-Dist: numpy ; extra == 'dev'
